{
    "4": [
        {
            "departure_time": "06:45:00",
            "route_id": "48"
        },
        {
            "departure_time": "06:06:00",
            "route_id": "48"
        },
        {
            "departure_time": "07:18:00",
            "route_id": "48"
        },
        {
            "departure_time": "05:38:00",
            "route_id": "49"
        },
        {
            "departure_time": "09:39:00",
            "route_id": "49"
        },
        {
            "departure_time": "19:38:00",
            "route_id": "49"
        },
        {
            "departure_time": "16:39:00",
            "route_id": "49"
        },
        {
            "departure_time": "14:09:00",
            "route_id": "49"
        },
        {
            "departure_time": "11:39:00",
            "route_id": "49"
        },
        {
            "departure_time": "13:09:00",
            "route_id": "49"
        },
        {
            "departure_time": "07:29:00",
            "route_id": "49"
        },
        {
            "departure_time": "18:38:00",
            "route_id": "49"
        },
        {
            "departure_time": "21:38:00",
            "route_id": "49"
        },
        {
            "departure_time": "12:39:00",
            "route_id": "49"
        },
        {
            "departure_time": "06:49:00",
            "route_id": "49"
        },
        {
            "departure_time": "22:38:00",
            "route_id": "49"
        },
        {
            "departure_time": "07:16:00",
            "route_id": "49"
        },
        {
            "departure_time": "18:08:00",
            "route_id": "49"
        },
        {
            "departure_time": "09:10:00",
            "route_id": "49"
        },
        {
            "departure_time": "21:08:00",
            "route_id": "49"
        },
        {
            "departure_time": "15:11:00",
            "route_id": "49"
        },
        {
            "departure_time": "14:39:00",
            "route_id": "49"
        },
        {
            "departure_time": "19:08:00",
            "route_id": "49"
        },
        {
            "departure_time": "13:39:00",
            "route_id": "49"
        },
        {
            "departure_time": "20:38:00",
            "route_id": "49"
        },
        {
            "departure_time": "12:09:00",
            "route_id": "49"
        },
        {
            "departure_time": "17:09:00",
            "route_id": "49"
        },
        {
            "departure_time": "16:11:00",
            "route_id": "49"
        },
        {
            "departure_time": "23:48:00",
            "route_id": "49"
        },
        {
            "departure_time": "24:18:00",
            "route_id": "49"
        },
        {
            "departure_time": "20:08:00",
            "route_id": "49"
        },
        {
            "departure_time": "23:08:00",
            "route_id": "49"
        },
        {
            "departure_time": "07:50:00",
            "route_id": "49"
        },
        {
            "departure_time": "11:09:00",
            "route_id": "49"
        },
        {
            "departure_time": "15:41:00",
            "route_id": "49"
        },
        {
            "departure_time": "17:39:00",
            "route_id": "49"
        },
        {
            "departure_time": "22:08:00",
            "route_id": "49"
        },
        {
            "departure_time": "10:09:00",
            "route_id": "49"
        },
        {
            "departure_time": "10:39:00",
            "route_id": "49"
        },
        {
            "departure_time": "06:21:00",
            "route_id": "49"
        },
        {
            "departure_time": "08:20:00",
            "route_id": "49"
        },
        {
            "departure_time": "08:40:00",
            "route_id": "49"
        },
        {
            "departure_time": "14:13:00",
            "route_id": "49"
        },
        {
            "departure_time": "15:04:00",
            "route_id": "51"
        },
        {
            "departure_time": "17:04:00",
            "route_id": "51"
        },
        {
            "departure_time": "19:03:00",
            "route_id": "51"
        },
        {
            "departure_time": "11:04:00",
            "route_id": "51"
        },
        {
            "departure_time": "13:04:00",
            "route_id": "51"
        },
        {
            "departure_time": "09:03:00",
            "route_id": "51"
        },
        {
            "departure_time": "21:03:00",
            "route_id": "51"
        },
        {
            "departure_time": "07:03:00",
            "route_id": "51"
        }
    ],
    "5": [
        {
            "departure_time": "06:06:00",
            "route_id": "48"
        },
        {
            "departure_time": "06:45:00",
            "route_id": "48"
        },
        {
            "departure_time": "07:18:00",
            "route_id": "48"
        },
        {
            "departure_time": "09:10:00",
            "route_id": "49"
        },
        {
            "departure_time": "12:09:00",
            "route_id": "49"
        },
        {
            "departure_time": "18:38:00",
            "route_id": "49"
        },
        {
            "departure_time": "23:08:00",
            "route_id": "49"
        },
        {
            "departure_time": "07:29:00",
            "route_id": "49"
        },
        {
            "departure_time": "15:11:00",
            "route_id": "49"
        },
        {
            "departure_time": "17:09:00",
            "route_id": "49"
        },
        {
            "departure_time": "13:09:00",
            "route_id": "49"
        },
        {
            "departure_time": "11:39:00",
            "route_id": "49"
        },
        {
            "departure_time": "20:08:00",
            "route_id": "49"
        },
        {
            "departure_time": "22:38:00",
            "route_id": "49"
        },
        {
            "departure_time": "21:38:00",
            "route_id": "49"
        },
        {
            "departure_time": "05:38:00",
            "route_id": "49"
        },
        {
            "departure_time": "07:50:00",
            "route_id": "49"
        },
        {
            "departure_time": "11:09:00",
            "route_id": "49"
        },
        {
            "departure_time": "23:48:00",
            "route_id": "49"
        },
        {
            "departure_time": "24:18:00",
            "route_id": "49"
        },
        {
            "departure_time": "07:16:00",
            "route_id": "49"
        },
        {
            "departure_time": "19:38:00",
            "route_id": "49"
        },
        {
            "departure_time": "15:41:00",
            "route_id": "49"
        },
        {
            "departure_time": "16:11:00",
            "route_id": "49"
        },
        {
            "departure_time": "19:08:00",
            "route_id": "49"
        },
        {
            "departure_time": "13:39:00",
            "route_id": "49"
        },
        {
            "departure_time": "09:39:00",
            "route_id": "49"
        },
        {
            "departure_time": "16:39:00",
            "route_id": "49"
        },
        {
            "departure_time": "18:08:00",
            "route_id": "49"
        },
        {
            "departure_time": "12:39:00",
            "route_id": "49"
        },
        {
            "departure_time": "06:49:00",
            "route_id": "49"
        },
        {
            "departure_time": "21:08:00",
            "route_id": "49"
        },
        {
            "departure_time": "17:39:00",
            "route_id": "49"
        },
        {
            "departure_time": "14:09:00",
            "route_id": "49"
        },
        {
            "departure_time": "14:39:00",
            "route_id": "49"
        },
        {
            "departure_time": "20:38:00",
            "route_id": "49"
        },
        {
            "departure_time": "22:08:00",
            "route_id": "49"
        },
        {
            "departure_time": "08:40:00",
            "route_id": "49"
        },
        {
            "departure_time": "06:21:00",
            "route_id": "49"
        },
        {
            "departure_time": "10:09:00",
            "route_id": "49"
        },
        {
            "departure_time": "08:20:00",
            "route_id": "49"
        },
        {
            "departure_time": "10:39:00",
            "route_id": "49"
        },
        {
            "departure_time": "11:04:00",
            "route_id": "51"
        },
        {
            "departure_time": "09:03:00",
            "route_id": "51"
        },
        {
            "departure_time": "17:04:00",
            "route_id": "51"
        },
        {
            "departure_time": "13:04:00",
            "route_id": "51"
        },
        {
            "departure_time": "19:03:00",
            "route_id": "51"
        },
        {
            "departure_time": "15:04:00",
            "route_id": "51"
        },
        {
            "departure_time": "21:03:00",
            "route_id": "51"
        },
        {
            "departure_time": "07:03:00",
            "route_id": "51"
        }
    ],
    "2": [
        {
            "departure_time": "07:18:00",
            "route_id": "48"
        },
        {
            "departure_time": "06:45:00",
            "route_id": "48"
        },
        {
            "departure_time": "06:06:00",
            "route_id": "48"
        },
        {
            "departure_time": "19:38:00",
            "route_id": "49"
        },
        {
            "departure_time": "14:39:00",
            "route_id": "49"
        },
        {
            "departure_time": "13:39:00",
            "route_id": "49"
        },
        {
            "departure_time": "21:08:00",
            "route_id": "49"
        },
        {
            "departure_time": "09:39:00",
            "route_id": "49"
        },
        {
            "departure_time": "12:39:00",
            "route_id": "49"
        },
        {
            "departure_time": "11:39:00",
            "route_id": "49"
        },
        {
            "departure_time": "15:11:00",
            "route_id": "49"
        },
        {
            "departure_time": "22:08:00",
            "route_id": "49"
        },
        {
            "departure_time": "23:08:00",
            "route_id": "49"
        },
        {
            "departure_time": "11:09:00",
            "route_id": "49"
        },
        {
            "departure_time": "13:09:00",
            "route_id": "49"
        },
        {
            "departure_time": "17:39:00",
            "route_id": "49"
        },
        {
            "departure_time": "07:29:00",
            "route_id": "49"
        },
        {
            "departure_time": "05:38:00",
            "route_id": "49"
        },
        {
            "departure_time": "18:08:00",
            "route_id": "49"
        },
        {
            "departure_time": "19:08:00",
            "route_id": "49"
        },
        {
            "departure_time": "16:11:00",
            "route_id": "49"
        },
        {
            "departure_time": "23:48:00",
            "route_id": "49"
        },
        {
            "departure_time": "14:09:00",
            "route_id": "49"
        },
        {
            "departure_time": "07:16:00",
            "route_id": "49"
        },
        {
            "departure_time": "15:41:00",
            "route_id": "49"
        },
        {
            "departure_time": "16:39:00",
            "route_id": "49"
        },
        {
            "departure_time": "21:38:00",
            "route_id": "49"
        },
        {
            "departure_time": "24:18:00",
            "route_id": "49"
        },
        {
            "departure_time": "17:09:00",
            "route_id": "49"
        },
        {
            "departure_time": "12:09:00",
            "route_id": "49"
        },
        {
            "departure_time": "20:08:00",
            "route_id": "49"
        },
        {
            "departure_time": "09:10:00",
            "route_id": "49"
        },
        {
            "departure_time": "06:49:00",
            "route_id": "49"
        },
        {
            "departure_time": "22:38:00",
            "route_id": "49"
        },
        {
            "departure_time": "18:38:00",
            "route_id": "49"
        },
        {
            "departure_time": "07:50:00",
            "route_id": "49"
        },
        {
            "departure_time": "20:38:00",
            "route_id": "49"
        },
        {
            "departure_time": "10:39:00",
            "route_id": "49"
        },
        {
            "departure_time": "10:09:00",
            "route_id": "49"
        },
        {
            "departure_time": "06:21:00",
            "route_id": "49"
        },
        {
            "departure_time": "08:40:00",
            "route_id": "49"
        },
        {
            "departure_time": "08:20:00",
            "route_id": "49"
        },
        {
            "departure_time": "15:04:00",
            "route_id": "51"
        },
        {
            "departure_time": "19:03:00",
            "route_id": "51"
        },
        {
            "departure_time": "13:04:00",
            "route_id": "51"
        },
        {
            "departure_time": "11:04:00",
            "route_id": "51"
        },
        {
            "departure_time": "09:03:00",
            "route_id": "51"
        },
        {
            "departure_time": "17:04:00",
            "route_id": "51"
        },
        {
            "departure_time": "21:03:00",
            "route_id": "51"
        },
        {
            "departure_time": "07:03:00",
            "route_id": "51"
        }
    ],
    "1": [
        {
            "departure_time": "07:18:00",
            "route_id": "48"
        },
        {
            "departure_time": "06:06:00",
            "route_id": "48"
        },
        {
            "departure_time": "06:45:00",
            "route_id": "48"
        },
        {
            "departure_time": "23:08:00",
            "route_id": "49"
        },
        {
            "departure_time": "17:09:00",
            "route_id": "49"
        },
        {
            "departure_time": "14:09:00",
            "route_id": "49"
        },
        {
            "departure_time": "13:09:00",
            "route_id": "49"
        },
        {
            "departure_time": "20:38:00",
            "route_id": "49"
        },
        {
            "departure_time": "20:08:00",
            "route_id": "49"
        },
        {
            "departure_time": "16:11:00",
            "route_id": "49"
        },
        {
            "departure_time": "12:09:00",
            "route_id": "49"
        },
        {
            "departure_time": "15:11:00",
            "route_id": "49"
        },
        {
            "departure_time": "07:29:00",
            "route_id": "49"
        },
        {
            "departure_time": "11:39:00",
            "route_id": "49"
        },
        {
            "departure_time": "09:10:00",
            "route_id": "49"
        },
        {
            "departure_time": "18:38:00",
            "route_id": "49"
        },
        {
            "departure_time": "21:38:00",
            "route_id": "49"
        },
        {
            "departure_time": "06:49:00",
            "route_id": "49"
        },
        {
            "departure_time": "22:38:00",
            "route_id": "49"
        },
        {
            "departure_time": "13:39:00",
            "route_id": "49"
        },
        {
            "departure_time": "16:39:00",
            "route_id": "49"
        },
        {
            "departure_time": "09:39:00",
            "route_id": "49"
        },
        {
            "departure_time": "17:39:00",
            "route_id": "49"
        },
        {
            "departure_time": "05:38:00",
            "route_id": "49"
        },
        {
            "departure_time": "11:09:00",
            "route_id": "49"
        },
        {
            "departure_time": "07:16:00",
            "route_id": "49"
        },
        {
            "departure_time": "19:38:00",
            "route_id": "49"
        },
        {
            "departure_time": "21:08:00",
            "route_id": "49"
        },
        {
            "departure_time": "12:39:00",
            "route_id": "49"
        },
        {
            "departure_time": "23:48:00",
            "route_id": "49"
        },
        {
            "departure_time": "18:08:00",
            "route_id": "49"
        },
        {
            "departure_time": "14:39:00",
            "route_id": "49"
        },
        {
            "departure_time": "22:08:00",
            "route_id": "49"
        },
        {
            "departure_time": "15:41:00",
            "route_id": "49"
        },
        {
            "departure_time": "19:08:00",
            "route_id": "49"
        },
        {
            "departure_time": "24:18:00",
            "route_id": "49"
        },
        {
            "departure_time": "07:50:00",
            "route_id": "49"
        },
        {
            "departure_time": "08:20:00",
            "route_id": "49"
        },
        {
            "departure_time": "10:39:00",
            "route_id": "49"
        },
        {
            "departure_time": "08:40:00",
            "route_id": "49"
        },
        {
            "departure_time": "10:09:00",
            "route_id": "49"
        },
        {
            "departure_time": "06:21:00",
            "route_id": "49"
        },
        {
            "departure_time": "11:04:00",
            "route_id": "51"
        },
        {
            "departure_time": "15:04:00",
            "route_id": "51"
        },
        {
            "departure_time": "09:03:00",
            "route_id": "51"
        },
        {
            "departure_time": "19:03:00",
            "route_id": "51"
        },
        {
            "departure_time": "17:04:00",
            "route_id": "51"
        },
        {
            "departure_time": "13:04:00",
            "route_id": "51"
        },
        {
            "departure_time": "21:03:00",
            "route_id": "51"
        },
        {
            "departure_time": "07:03:00",
            "route_id": "51"
        }
    ],
    "3": [
        {
            "departure_time": "07:18:00",
            "route_id": "48"
        },
        {
            "departure_time": "06:45:00",
            "route_id": "48"
        },
        {
            "departure_time": "06:06:00",
            "route_id": "48"
        },
        {
            "departure_time": "12:39:00",
            "route_id": "49"
        },
        {
            "departure_time": "22:38:00",
            "route_id": "49"
        },
        {
            "departure_time": "06:49:00",
            "route_id": "49"
        },
        {
            "departure_time": "09:39:00",
            "route_id": "49"
        },
        {
            "departure_time": "14:39:00",
            "route_id": "49"
        },
        {
            "departure_time": "18:08:00",
            "route_id": "49"
        },
        {
            "departure_time": "21:08:00",
            "route_id": "49"
        },
        {
            "departure_time": "20:08:00",
            "route_id": "49"
        },
        {
            "departure_time": "19:38:00",
            "route_id": "49"
        },
        {
            "departure_time": "22:08:00",
            "route_id": "49"
        },
        {
            "departure_time": "17:09:00",
            "route_id": "49"
        },
        {
            "departure_time": "24:18:00",
            "route_id": "49"
        },
        {
            "departure_time": "23:08:00",
            "route_id": "49"
        },
        {
            "departure_time": "20:38:00",
            "route_id": "49"
        },
        {
            "departure_time": "05:38:00",
            "route_id": "49"
        },
        {
            "departure_time": "15:41:00",
            "route_id": "49"
        },
        {
            "departure_time": "16:39:00",
            "route_id": "49"
        },
        {
            "departure_time": "19:08:00",
            "route_id": "49"
        },
        {
            "departure_time": "17:39:00",
            "route_id": "49"
        },
        {
            "departure_time": "07:16:00",
            "route_id": "49"
        },
        {
            "departure_time": "13:09:00",
            "route_id": "49"
        },
        {
            "departure_time": "11:09:00",
            "route_id": "49"
        },
        {
            "departure_time": "09:10:00",
            "route_id": "49"
        },
        {
            "departure_time": "07:50:00",
            "route_id": "49"
        },
        {
            "departure_time": "07:29:00",
            "route_id": "49"
        },
        {
            "departure_time": "18:38:00",
            "route_id": "49"
        },
        {
            "departure_time": "23:48:00",
            "route_id": "49"
        },
        {
            "departure_time": "14:09:00",
            "route_id": "49"
        },
        {
            "departure_time": "11:39:00",
            "route_id": "49"
        },
        {
            "departure_time": "13:39:00",
            "route_id": "49"
        },
        {
            "departure_time": "12:09:00",
            "route_id": "49"
        },
        {
            "departure_time": "21:38:00",
            "route_id": "49"
        },
        {
            "departure_time": "15:11:00",
            "route_id": "49"
        },
        {
            "departure_time": "16:11:00",
            "route_id": "49"
        },
        {
            "departure_time": "10:09:00",
            "route_id": "49"
        },
        {
            "departure_time": "08:20:00",
            "route_id": "49"
        },
        {
            "departure_time": "08:40:00",
            "route_id": "49"
        },
        {
            "departure_time": "10:39:00",
            "route_id": "49"
        },
        {
            "departure_time": "06:21:00",
            "route_id": "49"
        },
        {
            "departure_time": "13:04:00",
            "route_id": "51"
        },
        {
            "departure_time": "11:04:00",
            "route_id": "51"
        },
        {
            "departure_time": "15:04:00",
            "route_id": "51"
        },
        {
            "departure_time": "17:04:00",
            "route_id": "51"
        },
        {
            "departure_time": "19:03:00",
            "route_id": "51"
        },
        {
            "departure_time": "09:03:00",
            "route_id": "51"
        },
        {
            "departure_time": "21:03:00",
            "route_id": "51"
        },
        {
            "departure_time": "07:03:00",
            "route_id": "51"
        }
    ],
    "6": [
        {
            "departure_time": "19:07:00",
            "route_id": "49"
        },
        {
            "departure_time": "20:07:00",
            "route_id": "49"
        },
        {
            "departure_time": "07:38:00",
            "route_id": "49"
        },
        {
            "departure_time": "17:38:00",
            "route_id": "49"
        },
        {
            "departure_time": "14:08:00",
            "route_id": "49"
        },
        {
            "departure_time": "23:07:00",
            "route_id": "49"
        },
        {
            "departure_time": "07:08:00",
            "route_id": "49"
        },
        {
            "departure_time": "08:38:00",
            "route_id": "49"
        },
        {
            "departure_time": "20:37:00",
            "route_id": "49"
        },
        {
            "departure_time": "16:38:00",
            "route_id": "49"
        },
        {
            "departure_time": "21:37:00",
            "route_id": "49"
        },
        {
            "departure_time": "10:08:00",
            "route_id": "49"
        },
        {
            "departure_time": "14:38:00",
            "route_id": "49"
        },
        {
            "departure_time": "16:08:00",
            "route_id": "49"
        },
        {
            "departure_time": "13:38:00",
            "route_id": "49"
        },
        {
            "departure_time": "11:08:00",
            "route_id": "49"
        },
        {
            "departure_time": "15:08:00",
            "route_id": "49"
        },
        {
            "departure_time": "13:08:00",
            "route_id": "49"
        },
        {
            "departure_time": "19:37:00",
            "route_id": "49"
        },
        {
            "departure_time": "08:08:00",
            "route_id": "49"
        },
        {
            "departure_time": "18:08:00",
            "route_id": "49"
        },
        {
            "departure_time": "11:38:00",
            "route_id": "49"
        },
        {
            "departure_time": "09:08:00",
            "route_id": "49"
        },
        {
            "departure_time": "24:07:00",
            "route_id": "49"
        },
        {
            "departure_time": "12:08:00",
            "route_id": "49"
        },
        {
            "departure_time": "21:07:00",
            "route_id": "49"
        },
        {
            "departure_time": "22:07:00",
            "route_id": "49"
        },
        {
            "departure_time": "09:38:00",
            "route_id": "49"
        },
        {
            "departure_time": "18:37:00",
            "route_id": "49"
        },
        {
            "departure_time": "10:38:00",
            "route_id": "49"
        },
        {
            "departure_time": "17:08:00",
            "route_id": "49"
        },
        {
            "departure_time": "22:37:00",
            "route_id": "49"
        },
        {
            "departure_time": "15:38:00",
            "route_id": "49"
        },
        {
            "departure_time": "12:38:00",
            "route_id": "49"
        },
        {
            "departure_time": "11:03:00",
            "route_id": "51"
        },
        {
            "departure_time": "09:03:00",
            "route_id": "51"
        },
        {
            "departure_time": "13:03:00",
            "route_id": "51"
        },
        {
            "departure_time": "15:03:00",
            "route_id": "51"
        },
        {
            "departure_time": "17:03:00",
            "route_id": "51"
        },
        {
            "departure_time": "19:03:00",
            "route_id": "51"
        },
        {
            "departure_time": "21:03:00",
            "route_id": "51"
        }
    ],
    "8": [
        {
            "departure_time": "22:08:00",
            "route_id": "49"
        },
        {
            "departure_time": "12:08:00",
            "route_id": "49"
        },
        {
            "departure_time": "08:08:00",
            "route_id": "49"
        },
        {
            "departure_time": "16:08:00",
            "route_id": "49"
        },
        {
            "departure_time": "13:38:00",
            "route_id": "49"
        },
        {
            "departure_time": "16:38:00",
            "route_id": "49"
        },
        {
            "departure_time": "19:08:00",
            "route_id": "49"
        },
        {
            "departure_time": "11:38:00",
            "route_id": "49"
        },
        {
            "departure_time": "20:08:00",
            "route_id": "49"
        },
        {
            "departure_time": "17:08:00",
            "route_id": "49"
        },
        {
            "departure_time": "15:08:00",
            "route_id": "49"
        },
        {
            "departure_time": "10:38:00",
            "route_id": "49"
        },
        {
            "departure_time": "11:08:00",
            "route_id": "49"
        },
        {
            "departure_time": "23:07:00",
            "route_id": "49"
        },
        {
            "departure_time": "19:38:00",
            "route_id": "49"
        },
        {
            "departure_time": "13:08:00",
            "route_id": "49"
        },
        {
            "departure_time": "07:08:00",
            "route_id": "49"
        },
        {
            "departure_time": "09:08:00",
            "route_id": "49"
        },
        {
            "departure_time": "18:08:00",
            "route_id": "49"
        },
        {
            "departure_time": "10:08:00",
            "route_id": "49"
        },
        {
            "departure_time": "18:38:00",
            "route_id": "49"
        },
        {
            "departure_time": "15:38:00",
            "route_id": "49"
        },
        {
            "departure_time": "14:08:00",
            "route_id": "49"
        },
        {
            "departure_time": "17:38:00",
            "route_id": "49"
        },
        {
            "departure_time": "12:38:00",
            "route_id": "49"
        },
        {
            "departure_time": "21:08:00",
            "route_id": "49"
        },
        {
            "departure_time": "14:38:00",
            "route_id": "49"
        },
        {
            "departure_time": "15:03:00",
            "route_id": "51"
        },
        {
            "departure_time": "17:03:00",
            "route_id": "51"
        },
        {
            "departure_time": "11:03:00",
            "route_id": "51"
        },
        {
            "departure_time": "13:03:00",
            "route_id": "51"
        },
        {
            "departure_time": "19:03:00",
            "route_id": "51"
        },
        {
            "departure_time": "09:03:00",
            "route_id": "51"
        },
        {
            "departure_time": "21:03:00",
            "route_id": "51"
        }
    ],
    "7": [
        {
            "departure_time": "17:38:00",
            "route_id": "49"
        },
        {
            "departure_time": "13:38:00",
            "route_id": "49"
        },
        {
            "departure_time": "10:38:00",
            "route_id": "49"
        },
        {
            "departure_time": "18:08:00",
            "route_id": "49"
        },
        {
            "departure_time": "19:07:00",
            "route_id": "49"
        },
        {
            "departure_time": "17:08:00",
            "route_id": "49"
        },
        {
            "departure_time": "16:38:00",
            "route_id": "49"
        },
        {
            "departure_time": "22:07:00",
            "route_id": "49"
        },
        {
            "departure_time": "11:08:00",
            "route_id": "49"
        },
        {
            "departure_time": "09:08:00",
            "route_id": "49"
        },
        {
            "departure_time": "07:08:00",
            "route_id": "49"
        },
        {
            "departure_time": "21:37:00",
            "route_id": "49"
        },
        {
            "departure_time": "08:08:00",
            "route_id": "49"
        },
        {
            "departure_time": "24:07:00",
            "route_id": "49"
        },
        {
            "departure_time": "16:08:00",
            "route_id": "49"
        },
        {
            "departure_time": "12:38:00",
            "route_id": "49"
        },
        {
            "departure_time": "08:38:00",
            "route_id": "49"
        },
        {
            "departure_time": "20:37:00",
            "route_id": "49"
        },
        {
            "departure_time": "21:07:00",
            "route_id": "49"
        },
        {
            "departure_time": "22:37:00",
            "route_id": "49"
        },
        {
            "departure_time": "14:08:00",
            "route_id": "49"
        },
        {
            "departure_time": "07:38:00",
            "route_id": "49"
        },
        {
            "departure_time": "09:38:00",
            "route_id": "49"
        },
        {
            "departure_time": "18:37:00",
            "route_id": "49"
        },
        {
            "departure_time": "13:08:00",
            "route_id": "49"
        },
        {
            "departure_time": "15:38:00",
            "route_id": "49"
        },
        {
            "departure_time": "23:07:00",
            "route_id": "49"
        },
        {
            "departure_time": "20:07:00",
            "route_id": "49"
        },
        {
            "departure_time": "14:38:00",
            "route_id": "49"
        },
        {
            "departure_time": "15:08:00",
            "route_id": "49"
        },
        {
            "departure_time": "19:37:00",
            "route_id": "49"
        },
        {
            "departure_time": "12:08:00",
            "route_id": "49"
        },
        {
            "departure_time": "11:38:00",
            "route_id": "49"
        },
        {
            "departure_time": "10:08:00",
            "route_id": "49"
        },
        {
            "departure_time": "11:03:00",
            "route_id": "51"
        },
        {
            "departure_time": "17:03:00",
            "route_id": "51"
        },
        {
            "departure_time": "19:03:00",
            "route_id": "51"
        },
        {
            "departure_time": "13:03:00",
            "route_id": "51"
        },
        {
            "departure_time": "15:03:00",
            "route_id": "51"
        },
        {
            "departure_time": "09:03:00",
            "route_id": "51"
        },
        {
            "departure_time": "21:03:00",
            "route_id": "51"
        }
    ],
    "10": [
        {
            "departure_time": "22:08:00",
            "route_id": "49"
        },
        {
            "departure_time": "14:08:00",
            "route_id": "49"
        },
        {
            "departure_time": "14:38:00",
            "route_id": "49"
        },
        {
            "departure_time": "16:08:00",
            "route_id": "49"
        },
        {
            "departure_time": "10:08:00",
            "route_id": "49"
        },
        {
            "departure_time": "09:08:00",
            "route_id": "49"
        },
        {
            "departure_time": "18:08:00",
            "route_id": "49"
        },
        {
            "departure_time": "10:38:00",
            "route_id": "49"
        },
        {
            "departure_time": "18:38:00",
            "route_id": "49"
        },
        {
            "departure_time": "17:38:00",
            "route_id": "49"
        },
        {
            "departure_time": "08:08:00",
            "route_id": "49"
        },
        {
            "departure_time": "20:08:00",
            "route_id": "49"
        },
        {
            "departure_time": "11:38:00",
            "route_id": "49"
        },
        {
            "departure_time": "16:38:00",
            "route_id": "49"
        },
        {
            "departure_time": "11:08:00",
            "route_id": "49"
        },
        {
            "departure_time": "07:08:00",
            "route_id": "49"
        },
        {
            "departure_time": "12:38:00",
            "route_id": "49"
        },
        {
            "departure_time": "21:08:00",
            "route_id": "49"
        },
        {
            "departure_time": "13:38:00",
            "route_id": "49"
        },
        {
            "departure_time": "17:08:00",
            "route_id": "49"
        },
        {
            "departure_time": "19:38:00",
            "route_id": "49"
        },
        {
            "departure_time": "23:07:00",
            "route_id": "49"
        },
        {
            "departure_time": "13:08:00",
            "route_id": "49"
        },
        {
            "departure_time": "15:38:00",
            "route_id": "49"
        },
        {
            "departure_time": "15:08:00",
            "route_id": "49"
        },
        {
            "departure_time": "19:08:00",
            "route_id": "49"
        },
        {
            "departure_time": "12:08:00",
            "route_id": "49"
        },
        {
            "departure_time": "11:03:00",
            "route_id": "51"
        },
        {
            "departure_time": "19:03:00",
            "route_id": "51"
        },
        {
            "departure_time": "09:03:00",
            "route_id": "51"
        },
        {
            "departure_time": "17:03:00",
            "route_id": "51"
        },
        {
            "departure_time": "15:03:00",
            "route_id": "51"
        },
        {
            "departure_time": "13:03:00",
            "route_id": "51"
        },
        {
            "departure_time": "21:03:00",
            "route_id": "51"
        }
    ],
    "9": [
        {
            "departure_time": "11:38:00",
            "route_id": "49"
        },
        {
            "departure_time": "12:38:00",
            "route_id": "49"
        },
        {
            "departure_time": "21:08:00",
            "route_id": "49"
        },
        {
            "departure_time": "22:08:00",
            "route_id": "49"
        },
        {
            "departure_time": "14:38:00",
            "route_id": "49"
        },
        {
            "departure_time": "23:07:00",
            "route_id": "49"
        },
        {
            "departure_time": "18:38:00",
            "route_id": "49"
        },
        {
            "departure_time": "19:08:00",
            "route_id": "49"
        },
        {
            "departure_time": "10:38:00",
            "route_id": "49"
        },
        {
            "departure_time": "11:08:00",
            "route_id": "49"
        },
        {
            "departure_time": "09:08:00",
            "route_id": "49"
        },
        {
            "departure_time": "18:08:00",
            "route_id": "49"
        },
        {
            "departure_time": "10:08:00",
            "route_id": "49"
        },
        {
            "departure_time": "17:08:00",
            "route_id": "49"
        },
        {
            "departure_time": "19:38:00",
            "route_id": "49"
        },
        {
            "departure_time": "16:38:00",
            "route_id": "49"
        },
        {
            "departure_time": "12:08:00",
            "route_id": "49"
        },
        {
            "departure_time": "20:08:00",
            "route_id": "49"
        },
        {
            "departure_time": "15:38:00",
            "route_id": "49"
        },
        {
            "departure_time": "15:08:00",
            "route_id": "49"
        },
        {
            "departure_time": "14:08:00",
            "route_id": "49"
        },
        {
            "departure_time": "13:38:00",
            "route_id": "49"
        },
        {
            "departure_time": "17:38:00",
            "route_id": "49"
        },
        {
            "departure_time": "16:08:00",
            "route_id": "49"
        },
        {
            "departure_time": "13:08:00",
            "route_id": "49"
        },
        {
            "departure_time": "07:08:00",
            "route_id": "49"
        },
        {
            "departure_time": "08:08:00",
            "route_id": "49"
        },
        {
            "departure_time": "15:03:00",
            "route_id": "51"
        },
        {
            "departure_time": "11:03:00",
            "route_id": "51"
        },
        {
            "departure_time": "13:03:00",
            "route_id": "51"
        },
        {
            "departure_time": "09:03:00",
            "route_id": "51"
        },
        {
            "departure_time": "19:03:00",
            "route_id": "51"
        },
        {
            "departure_time": "17:03:00",
            "route_id": "51"
        },
        {
            "departure_time": "21:03:00",
            "route_id": "51"
        }
    ]
}